README.md
setup.py
mldas/__init__.py
mldas/assess.py
mldas/gather.py
mldas/parallel.py
mldas/parse.py
mldas/prepare.py
mldas/scaletune.py
mldas/segmentation.py
mldas/selection.py
mldas/train.py
mldas.egg-info/PKG-INFO
mldas.egg-info/SOURCES.txt
mldas.egg-info/dependency_links.txt
mldas.egg-info/requires.txt
mldas.egg-info/top_level.txt
mldas/datasets/__init__.py
mldas/datasets/dataset.py
mldas/datasets/util.py
mldas/explore/__init__.py
mldas/explore/colormap.py
mldas/explore/convert.py
mldas/explore/distrib.py
mldas/explore/evaluation.py
mldas/explore/figures.py
mldas/explore/loading.py
mldas/explore/lookup.py
mldas/explore/mapping.py
mldas/explore/prepare.py
mldas/explore/single.py
mldas/explore/stacking.py
mldas/explore/xcorr.py
mldas/models/__init__.py
mldas/models/resnet.py
mldas/trainers/__init__.py
mldas/trainers/base.py
mldas/trainers/gan.py
mldas/trainers/generic.py
mldas/utils/__init__.py
mldas/utils/distributed.py
mldas/utils/logging.py