Metadata-Version: 2.1
Name: mldas
Version: 1.0.2
Summary: Machine learning analysis tools for Distributed Acoustic Sensing data.
Home-page: https://ml4science.gitlab.io/mldas
Author: Vincent Dumont
Author-email: vincentdumont11@gmail.com
Maintainer: Vincent Dumont
Maintainer-email: vincentdumont11@gmail.com
License: UNKNOWN
Project-URL: Source Code, https://gitlab.com/ml4science/mldas
Platform: UNKNOWN
Classifier: Intended Audience :: Science/Research
Classifier: License :: Other/Proprietary License
Classifier: Natural Language :: English
Classifier: Operating System :: OS Independent
Classifier: Programming Language :: Python
Classifier: Topic :: Scientific/Engineering :: Artificial Intelligence
Classifier: Topic :: Scientific/Engineering :: Physics
